jetblack_markdown/__init__.py
jetblack_markdown/autodoc.py
jetblack_markdown/autodoc_processor.py
jetblack_markdown/latex2mathml.py
jetblack_markdown/latex2mathml_processor.py
jetblack_markdown/py.typed
jetblack_markdown/utils.py
jetblack_markdown/metadata/__init__.py
jetblack_markdown/metadata/arguments.py
jetblack_markdown/metadata/callables.py
jetblack_markdown/metadata/classes.py
jetblack_markdown/metadata/common.py
jetblack_markdown/metadata/modules.py
jetblack_markdown/metadata/properties.py
jetblack_markdown/metadata/raises.py
jetblack_markdown/metadata/utils.py
jetblack_markdown/templates/macros.jinja2
jetblack_markdown/templates/macros_verbose.jinja2
jetblack_markdown/templates/main.jinja2
jetblack_markdown/templates/main_verbose.jinja2
jetblack_markdown-1.2.0.dist-info/METADATA
jetblack_markdown-1.2.0.dist-info/WHEEL
jetblack_markdown-1.2.0.dist-info/top_level.txt
jetblack_markdown-1.2.0.dist-info/RECORD
