Metadata-Version: 2.1
Name: jetblack-markdown
Version: 1.2.0
Summary: A markdown extension for python documentation
Author-email: Rob Blackbourn <rob.blackbourn@gmail.com>
License: Apache-2.0
Project-URL: Repository, https://github.com/rob-blackbourn/jetblack-markdown
Project-URL: Documentation, https://rob-blackbourn.github.io/jetblack-markdown
Project-URL: Issues, https://github.com/rob-blackbourn/jetblack-markdown/issues
Classifier: Programming Language :: Python :: 3
Classifier: License :: OSI Approved :: Apache Software License
Classifier: Operating System :: OS Independent
Requires-Python: >=3.8
Requires-Dist: markdown <4,>=3.5.1
Requires-Dist: docstring-parser ==0.15
Requires-Dist: latex2mathml ==3.77.0
